pyplane-1.12.5.dist-info/top_level.txt
pyplane-1.12.5.dist-info/METADATA
pyplane-1.12.5.dist-info/RECORD
pyplane-1.12.5.dist-info/WHEEL
pyplane/pyplane.cpython-38-x86_64-linux-gnu.so
pyplane/__init__.py
