Metadata-Version: 2.1
Name: pyplane
Version: 1.12.5
Summary: Interface to INI's CoACH class-chip via Teensy based PLANE (Platform for Learning About Neuromorphic Engineering).
Home-page: http://www.ini.uzh.ch/
Author: INI NCS
Author-email: something@unsupported.com
License: UNKNOWN
Platform: UNKNOWN
